hive_bt
